aiodinweb/__init__.py
aiodinweb/api.py
aiodinweb/constants.py
aiodinweb/containers.py
aiodinweb/content_type_resolvers.py
aiodinweb/cors.py
aiodinweb/data_structures.py
aiodinweb/decorators.py
aiodinweb/exceptions.py
aiodinweb/json_schema.py
aiodinweb/openapi.py
aiodinweb/operation.py
aiodinweb/resources.py
aiodinweb/web.py
aiodinweb/middleware/__init__.py
aiodinweb/static-ui/bundle.js
aiodinweb/static-ui/favicon-16x16.png
aiodinweb/static-ui/favicon-32x32.png
aiodinweb/static-ui/standalone-preset.js
aiodinweb/static-ui/ui.css
aiodinweb/static-ui/ui.html
aiodinweb/utils/__init__.py
aiodinweb/utils/sequences.py
aiodinweb-0.1.1.dist-info/METADATA
aiodinweb-0.1.1.dist-info/RECORD
aiodinweb-0.1.1.dist-info/WHEEL
aiodinweb-0.1.1.dist-info/pbr.json
aiodinweb-0.1.1.dist-info/top_level.txt
