Metadata-Version: 2.1
Name: aiodinweb
Version: 0.1.1
Summary: Toolkit for building web API's using Odin and `aiohttp`.
Home-page: https://github.com/python-odin/aiodinweb
Author: Tim Savage
Author-email: tim@savage.company
License: BSD
Keywords: web
Requires-Dist: aiohttp
Requires-Dist: odin
